dirscan/__init__.py
dirscan/__main__.py
dirscan/dirscan.py
dirscan/fileinfo.py
dirscan/scanfile.py
dirscan-0.9.dist-info/METADATA
dirscan-0.9.dist-info/RECORD
dirscan-0.9.dist-info/WHEEL
dirscan-0.9.dist-info/entry_points.txt
dirscan-0.9.dist-info/top_level.txt
