Metadata-Version: 2.1
Name: dirscan
Version: 0.9
Summary: Directory traverser
Home-page: https://github.com/sveinse/dirscan
Author: Svein Seldal
Author-email: sveinse@seldal.com
License: GPL3
Keywords: utility directory
Platform: UNKNOWN
Classifier: Development Status :: 4 - Beta
Classifier: Intended Audience :: Developers
Classifier: Intended Audience :: System Administrators
Classifier: Topic :: Utilities
Classifier: License :: OSI Approved :: GNU General Public License v3 (GPLv3)
Classifier: Programming Language :: Python :: 2
Classifier: Programming Language :: Python :: 2.7
Classifier: Programming Language :: Python :: 3
Classifier: Programming Language :: Python :: 3.6
